{	"primitives": {		"color-black-black-a-90": "#000000e5",		"color-black-black-a-100": "#000000",		"color-black-black-a-75": "#000000bf",		"color-black-black-a-60": "#00000099",		"color-black-black-a-45": "#00000072",		"color-black-black-a-30": "#0000004c",		"color-blue-blue-10": "#f6fbff",		"color-blue-blue-20": "#e8f3ff",		"color-blue-blue-30": "#d2e9ff",		"color-blue-blue-40": "#aad6ff",		"color-blue-blue-50": "#71b7fb",		"color-blue-blue-60": "#378fe9",		"color-blue-blue-70": "#0a66c2",		"color-blue-blue-80": "#004182",		"color-blue-blue-90": "#053059",		"color-blue-blue-100": "#0a2037",		"color-white-white": "#ffffff",		"color-system-gray-system-gray-60-a-10": "#8c8c8c19",		"color-system-gray-system-gray-60-a-15": "#8c8c8c26",		"color-system-gray-system-gray-60-a-20": "#8c8c8c33",		"color-system-gray-system-gray-60-a-25": "#8c8c8c3f",		"color-system-gray-system-gray-60-a-30": "#8c8c8c4c",		"color-system-gray-system-gray-60-a-35": "#8c8c8c59",		"color-system-gray-system-gray-60-a-40": "#8c8c8c66",		"color-system-gray-system-gray-60-a-45": "#8c8c8c72",		"color-warm-gray-warm-gray-10": "#fbfaf8",		"color-warm-gray-warm-gray-20": "#f4f2ee",		"color-warm-gray-warm-gray-30": "#eae6df",		"color-warm-gray-warm-gray-40": "#d6cec2",		"color-warm-gray-warm-gray-50": "#bbb1a1",		"color-warm-gray-warm-gray-60": "#958b7b",		"color-warm-gray-warm-gray-70": "#6e6558",		"color-warm-gray-warm-gray-80": "#474139",		"color-warm-gray-warm-gray-90": "#322f29",		"color-warm-gray-warm-gray-100": "#211f1c",		"color-blue-blue-5": "#f5f7f9",		"color-cool-gray-cool-gray-10": "#f8fafd",		"color-cool-gray-cool-gray-20": "#edf3f8",		"color-cool-gray-cool-gray-30": "#dde7f1",		"color-cool-gray-cool-gray-40": "#c2d3e4",		"color-cool-gray-cool-gray-50": "#9eb5ca",		"color-cool-gray-cool-gray-60": "#788fa5",		"color-cool-gray-cool-gray-70": "#56687a",		"color-cool-gray-cool-gray-80": "#38434f",		"color-cool-gray-cool-gray-90": "#293037",		"color-cool-gray-cool-gray-100": "#1b1f23",		"color-white-white-a-0": "#ffffff00",		"color-white-white-a-30": "#ffffff4c",		"color-white-white-a-45": "#ffffff72",		"color-white-white-a-60": "#ffffff99",		"color-white-white-a-75": "#ffffffbf",		"color-white-white-a-90": "#ffffffe5",		"color-white-white-a-100": "#ffffff",		"color-purple-purple-10": "#fcfaff",		"color-purple-purple-20": "#f7efff",		"color-purple-purple-30": "#efe0ff",		"color-purple-purple-40": "#e0c7fc",		"color-purple-purple-50": "#c8a1f6",		"color-purple-purple-60": "#a871ea",		"color-purple-purple-70": "#8443ce",		"color-purple-purple-80": "#592099",		"color-purple-purple-90": "#40176f",		"color-purple-purple-100": "#2a1245",		"color-system-red-system-red-10": "#fff9fa",		"color-system-red-system-red-20": "#ffeef1",		"color-system-red-system-red-30": "#ffdee3",		"color-system-red-system-red-40": "#ffc1ca",		"color-system-red-system-red-50": "#fd93a3",		"color-system-red-system-red-60": "#f3536b",		"color-system-red-system-red-70": "#cb112d",		"color-system-red-system-red-80": "#8a0015",		"color-system-red-system-red-90": "#640312",		"color-system-red-system-red-100": "#410911",		"color-amber-amber-10": "#fdfaf5",		"color-amber-amber-20": "#fdf0de",		"color-amber-amber-30": "#fde2bc",		"color-amber-amber-40": "#f9c982",		"color-amber-amber-50": "#e9a53f",		"color-amber-amber-60": "#c37d16",		"color-amber-amber-70": "#915907",		"color-amber-amber-80": "#5c3b09",		"color-amber-amber-90": "#402b0c",		"color-amber-amber-100": "#271d10",		"color-system-green-system-green-10": "#f0fdf9",		"color-system-green-system-green-20": "#d6faee",		"color-system-green-system-green-30": "#aff4dd",		"color-system-green-system-green-40": "#74e5c0",		"color-system-green-system-green-50": "#37c898",		"color-system-green-system-green-60": "#0f9f6f",		"color-system-green-system-green-70": "#01754f",		"color-system-green-system-green-80": "#004c33",		"color-system-green-system-green-90": "#013726",		"color-system-green-system-green-100": "#022419",		"color-system-orange-system-orange-10": "#fff9f5",		"color-system-orange-system-orange-20": "#ffefe5",		"color-system-orange-system-orange-30": "#ffe0cc",		"color-system-orange-system-orange-40": "#ffc5a0",		"color-system-orange-system-orange-50": "#fe9958",		"color-system-orange-system-orange-60": "#e06a1a",		"color-system-orange-system-orange-70": "#ad4601",		"color-system-orange-system-orange-80": "#702f03",		"color-system-orange-system-orange-90": "#4c240a",		"color-system-orange-system-orange-100": "#2f1a0d",		"color-blue-blue-60-a-10": "#378fe919",		"color-blue-blue-60-a-20": "#378fe933"	},	"tokens": {		"text-color-text": "VariableID:7:9",		"text-color-text-hover": "VariableID:7:9",		"text-color-text-active": "VariableID:7:9",		"text-color-text-meta": "VariableID:7:12",		"text-color-text-meta-hover": "VariableID:7:9",		"text-color-text-meta-active": "VariableID:7:9",		"text-color-text-overlay": "VariableID:7:25",		"text-color-text-overlay-hover": "VariableID:7:25",		"text-color-text-overlay-active": "VariableID:7:25",		"text-color-text-disabled": "VariableID:7:14",		"link-color-link": "VariableID:7:21",		"link-color-link-hover": "VariableID:7:22",		"link-color-link-active": "VariableID:7:22",		"background-color-background": "VariableID:7:25",		"background-color-background-neutral-soft": "VariableID:12:26",		"background-color-background-neutral-strong": "VariableID:12:27",		"border-color-border": "VariableID:7:11",		"border-color-border-hover": "VariableID:7:9",		"border-color-border-active": "VariableID:7:9",		"border-color-border-faint": "VariableID:10:4",		"border-color-border-faint-hover": "VariableID:10:6",		"border-color-border-faint-active": "VariableID:10:8",		"border-color-border-subtle": "VariableID:7:14",		"border-color-border-subtle-hover": "VariableID:7:13",		"border-color-border-subtle-active": "VariableID:7:13",		"label-color-label": "VariableID:7:11",		"icon-color-icon": "VariableID:7:11",		"icon-color-icon-hover": "VariableID:7:9",		"icon-color-icon-active": "VariableID:7:9",		"icon-color-icon-disabled": "VariableID:7:14",		"surface-color-surface-tint": "VariableID:7:15",		"shadow-color-shadow": "VariableID:7:14",		"shadow-color-shadow-supplemental": "VariableID:10:4",		"accent-color-accent-4": "VariableID:38:179",		"accent-color-accent-4-hover": "VariableID:38:180",		"accent-color-accent-4-active": "VariableID:38:180",		"action-color-action": "VariableID:7:21",		"action-color-action-hover": "VariableID:7:22",		"action-color-action-active": "VariableID:7:22",		"border-color-border-disabled": "VariableID:7:14",		"border-color-border-knockout": "VariableID:7:25",		"border-color-border-knockout-hover": "VariableID:7:25",		"label-color-label-hover": "VariableID:7:9",		"label-color-label-active": "VariableID:7:9",		"link-color-link-visited": "VariableID:42:331",		"link-color-link-visited-hover": "VariableID:42:332",		"link-color-link-visited-active": "VariableID:42:332",		"background-color-background-offset": "VariableID:12:26",		"background-color-mobile-background-offset": "VariableID:12:27",		"background-color-background-knockout": "VariableID:7:25",		"background-color-background-knockout-hover": "VariableID:7:25",		"background-color-background-knockout-active": "VariableID:42:320",		"background-color-background-disabled": "VariableID:10:4",		"text-color-text-negative": "VariableID:42:527",		"text-color-text-negative-hover": "VariableID:42:528",		"text-color-text-negative-active": "VariableID:42:529",		"surface-color-surface-tint-hover": "VariableID:7:16",		"surface-color-surface-tint-active": "VariableID:7:16",		"premium-color-premium-brand": "VariableID:42:721",		"premium-color-premium-text-brand": "VariableID:42:723",		"premium-color-premium-inbug": "VariableID:42:723",		"premium-color-premium-button-background": "VariableID:42:721",		"premium-color-premium-button-background-hover": "VariableID:42:722",		"premium-color-premium-button-background-active": "VariableID:42:723",		"brand-color-logo-brand": "VariableID:7:21",		"brand-color-logo-mono": "VariableID:7:10",		"background-color-background-tint-soft": "VariableID:7:16",		"action-color-action-disabled": "VariableID:7:14",		"positive-color-positive": "VariableID:61:3276",		"positive-color-positive-hover": "VariableID:61:3277",		"positive-color-positive-active": "VariableID:61:3277",		"background-color-background-positive-strong": "VariableID:61:3272",		"background-color-background-positive-soft": "VariableID:61:3271",		"background-color-background-negative-strong": "VariableID:42:523",		"background-color-background-negative-soft": "VariableID:42:522",		"negative-color-negative": "VariableID:42:527",		"negative-color-negative-hover": "VariableID:42:528",		"negative-color-negative-active": "VariableID:42:528",		"icon-color-icon-knockout": "VariableID:7:25",		"icon-color-icon-knockout-hover": "VariableID:7:25",		"icon-color-icon-knockout-active": "VariableID:42:320",		"label-color-label-knockout": "VariableID:7:25",		"label-color-label-knockout-hover": "VariableID:7:25",		"label-color-label-knockout-active": "VariableID:42:320",		"label-color-label-disabled": "VariableID:7:14",		"background-color-background-transparent": "VariableID:42:317",		"background-color-background-transparent-hover": "VariableID:10:2",		"background-color-background-transparent-active": "VariableID:10:4",		"action-color-background-action-transparent-hover": "VariableID:69:3834",		"action-color-background-action-transparent-active": "VariableID:69:3835",		"background-color-background-overlay": "VariableID:7:11",		"background-color-background-overlay-hover": "VariableID:7:9",		"background-color-background-overlay-active": "VariableID:7:9",		"link-color-link-disabled": "VariableID:7:14",		"track-color-track": "VariableID:7:12",		"neutral-color-neutral": "VariableID:38:179",		"neutral-color-neutral-hover": "VariableID:38:180",		"neutral-color-neutral-active": "VariableID:38:180",		"text-color-text-positive": "VariableID:61:3276",		"text-color-text-positive-hover": "VariableID:61:3277",		"text-color-text-positive-active": "VariableID:61:3277",		"text-color-text-neutral": "VariableID:38:179",		"text-color-text-neutral-hover": "VariableID:38:180",		"text-color-text-neutral-active": "VariableID:38:180"	}}